phobius_utils-0.1.1.dist-info/licenses/LICENSE
phobiusutils/__init__.py
phobiusutils/log.py
phobiusutils/test_suit.py
phobiusutils/watchdog.py
phobius_utils-0.1.1.dist-info/METADATA
phobius_utils-0.1.1.dist-info/WHEEL
phobius_utils-0.1.1.dist-info/top_level.txt
phobius_utils-0.1.1.dist-info/RECORD
