Metadata-Version: 2.4
Name: phobius-utils
Version: 0.1.1
Summary: Using for me
Home-page: https://tuanca2503.github.io/
Author: MetaPhobius
Author-email: metaphobius@gmail.com
License: MIT
Classifier: Programming Language :: Python :: 3
Classifier: License :: OSI Approved :: MIT License
Classifier: Operating System :: OS Independent
Requires-Python: >=3.8
License-File: LICENSE
Requires-Dist: psutil==7.0.0
Requires-Dist: pympler
Dynamic: author
Dynamic: author-email
Dynamic: classifier
Dynamic: description
Dynamic: description-content-type
Dynamic: home-page
Dynamic: license
Dynamic: license-file
Dynamic: requires-dist
Dynamic: requires-python
Dynamic: summary
